MANIFEST.in
README.txt
setup.py
collective/__init__.py
collective.comicbookreader.egg-info/PKG-INFO
collective.comicbookreader.egg-info/SOURCES.txt
collective.comicbookreader.egg-info/dependency_links.txt
collective.comicbookreader.egg-info/entry_points.txt
collective.comicbookreader.egg-info/namespace_packages.txt
collective.comicbookreader.egg-info/not-zip-safe
collective.comicbookreader.egg-info/paster_plugins.txt
collective.comicbookreader.egg-info/requires.txt
collective.comicbookreader.egg-info/top_level.txt
collective/comicbookreader/__init__.py
collective/comicbookreader/config.py
collective/comicbookreader/configure.zcml
collective/comicbookreader/i18n.sh
collective/comicbookreader/tests.py
collective/comicbookreader/browser/__init__.py
collective/comicbookreader/browser/cbrpresentation.pt
collective/comicbookreader/browser/cbrview.pt
collective/comicbookreader/browser/configure.zcml
collective/comicbookreader/browser/extract.py
collective/comicbookreader/browser/interfaces.py
collective/comicbookreader/browser/view.py
collective/comicbookreader/browser/images/controls.png
collective/comicbookreader/browser/images/controls.xcf
collective/comicbookreader/browser/images/gradient-menu.png
collective/comicbookreader/browser/images/icons-site.txt
collective/comicbookreader/browser/images/switch.png
collective/comicbookreader/browser/javascript/cbr.js
collective/comicbookreader/browser/stylesheets/cbr.css
collective/comicbookreader/locales/collective.comicbookreader.pot
collective/comicbookreader/locales/en/LC_MESSAGES/collective.comicbookreader.mo
collective/comicbookreader/locales/en/LC_MESSAGES/collective.comicbookreader.po
collective/comicbookreader/locales/it/LC_MESSAGES/collective.comicbookreader.mo
collective/comicbookreader/locales/it/LC_MESSAGES/collective.comicbookreader.po
collective/comicbookreader/profiles/default/browserlayer.xml
collective/comicbookreader/profiles/default/cssregistry.xml
collective/comicbookreader/profiles/default/jsregistry.xml
collective/comicbookreader/profiles/default/metadata.xml
collective/comicbookreader/profiles/default/types/File.xml
docs/HISTORY.txt
docs/INSTALL.txt
docs/LICENSE.GPL
docs/LICENSE.txt