Metadata-Version: 1.0
Name: collective.comicbookreader
Version: 1.0
Summary: An inline comic book reader for plone
Home-page: https://github.com/giacomos/collective.comicbookreader
Author: Giacomo Spettoli
Author-email: giacomo.spettoli@gmail.com
License: GPL
Keywords: zope plone comic book reader
Platform: UNKNOWN
Classifier: Framework :: Plone
Classifier: Programming Language :: Python
